vocab_coverage/__init__.py
vocab_coverage/cache.py
vocab_coverage/charsets_char.json
vocab_coverage/charsets_token.json
vocab_coverage/classifier.py
vocab_coverage/constants.py
vocab_coverage/coverage.py
vocab_coverage/crawler.py
vocab_coverage/dataset_sentence_long.json
vocab_coverage/dataset_sentence_short.json
vocab_coverage/dict_word.json
vocab_coverage/draw.py
vocab_coverage/embedding.py
vocab_coverage/generate.py
vocab_coverage/lexicon.py
vocab_coverage/loader.py
vocab_coverage/main.py
vocab_coverage/models.yaml
vocab_coverage/models_readme.yaml
vocab_coverage/reducer.py
vocab_coverage/utils.py
vocab_coverage-0.9.dist-info/LICENSE
vocab_coverage-0.9.dist-info/METADATA
vocab_coverage-0.9.dist-info/WHEEL
vocab_coverage-0.9.dist-info/entry_points.txt
vocab_coverage-0.9.dist-info/top_level.txt
vocab_coverage-0.9.dist-info/RECORD
