Metadata-Version: 2.1
Name: vocab-coverage
Version: 0.9
Summary: 语言模型中文识字率分析
Home-page: https://github.com/twang2218/vocab-coverage
Author: Tao Wang
Author-email: twang2218@gmail.com
License: Apache License 2.0
Platform: UNKNOWN
Classifier: Development Status :: 3 - Alpha
Classifier: Intended Audience :: Developers
Classifier: Intended Audience :: Education
Classifier: Intended Audience :: Science/Research
Classifier: License :: OSI Approved :: Apache Software License
Classifier: Operating System :: OS Independent
Classifier: Programming Language :: Python :: 3
Classifier: Topic :: Scientific/Engineering :: Artificial Intelligence
Classifier: Topic :: Scientific/Engineering :: Information Analysis
Classifier: Topic :: Text Processing :: Linguistic
License-File: LICENSE
Requires-Dist: Pillow
Requires-Dist: protobuf (==3.20.0)
Requires-Dist: sentencepiece
Requires-Dist: tiktoken
Requires-Dist: torch
Requires-Dist: transformers
Requires-Dist: beautifulsoup4
Requires-Dist: bs4
Requires-Dist: pandas
Requires-Dist: requests
Requires-Dist: scikit-learn
Requires-Dist: accelerate
Requires-Dist: openai
Requires-Dist: python-dotenv
Requires-Dist: umap-learn
Requires-Dist: einops
Requires-Dist: transformers-stream-generator
Provides-Extra: cuml
Requires-Dist: cudf-cu12 ; extra == 'cuml'
Requires-Dist: cuml-cu12 ; extra == 'cuml'
Provides-Extra: datasets
Requires-Dist: harvesttext ; extra == 'datasets'
Requires-Dist: matplotlib ; extra == 'datasets'
Requires-Dist: cmaps ; extra == 'datasets'
